mrfi/__init__.py
mrfi/easyconfig_presets.py
mrfi/error_mode.py
mrfi/experiment.py
mrfi/mrfi.py
mrfi/observer.py
mrfi/quantization.py
mrfi/selector.py
MRFI-2.0.0.dist-info/LICENSE
MRFI-2.0.0.dist-info/METADATA
MRFI-2.0.0.dist-info/WHEEL
MRFI-2.0.0.dist-info/top_level.txt
MRFI-2.0.0.dist-info/RECORD
