Metadata-Version: 2.1
Name: MRFI
Version: 2.0.0
Summary: A multi-resolution DNN fault injection tool
Author-email: fffasttime <fffasttime@outlook.com>
License: MIT
Project-URL: Homepage, https://github.com/fffasttime/MRFI
Project-URL: Documentation, https://fffasttime.github.io/MRFI
Project-URL: Repository, https://github.com/fffasttime/MRFI.git
Keywords: PyTorch,reliability,FaultInjection,FaultTolerance
Classifier: Programming Language :: Python :: 3
Classifier: License :: OSI Approved :: MIT License
Classifier: Operating System :: OS Independent
Requires-Python: >=3.7
License-File: LICENSE
Requires-Dist: torchvision (>=0.11)
Requires-Dist: numpy (>=1.21)
Requires-Dist: PyYAML
Requires-Dist: scipy
Requires-Dist: torch (>=1.9)
